{
  "welcome": "🦅 Добро пожаловать в HawkX! *[DEVNET]*\n\nПробный период активен — комиссия 0.3%.\n\nВаш инвайт-код: `{inviteCode}`",
  "trial.active": "✅ Пробный период — {rate}% ещё {days} дней.",
  "trial.warning": "⚠️ Пробный период заканчивается через 24 часа!",
  "trial.expired": "Пробный период завершён. Ранг Scout — 1.00%.",
  "rank.up": "🦅 Повышение ранга! *{rank}*\nНовая комиссия: {fee}%",
  "killswitch.active": "⏸ Торговля приостановлена.",
  "trade.buy.success": "✅ Покупка выполнена! [DEVNET]\nТокен: {token}\nКомиссия: {fee} SOL",
  "trade.sell.success": "✅ Продажа выполнена! [DEVNET]\nP&L: {pnl}%",
  "trade.blocked.safety": "🚫 Сделка заблокирована: {reason}",
  "honeypot.detected": "🚫 Обнаружен honeypot.",
  "error.generic": "❌ Произошла ошибка.",
  "menu.fee": "Комиссия: {fee}% | {rank}",
  "menu.trial": "🟡 Пробный 0.3%",
  "settings.saved": "✅ Сохранено.",
  "wallet.added": "✅ Кошелёк добавлен: `{address}`",
  "wallet.limit": "❌ Достигнут лимит ({limit} кошельков).",
  "referral.payout": "💰 Реферальные выплаты: {sol} SOL",
  "onboarding.wallet": "👛 Добавьте первый кошелёк.",
  "rank.scout": "Scout",
  "rank.tracker": "Tracker",
  "rank.hunter": "Hunter",
  "rank.predator": "Predator",
  "rank.apex": "Apex",
  "rank.hawk": "Hawk",
  "rank.hawkelite": "Hawk Elite"
}
